django_ace_widget/__init__.py
django_ace_widget/admin.py
django_ace_widget/apps.py
django_ace_widget/models.py
django_ace_widget/tests.py
django_ace_widget/views.py
django_ace_widget/widgets.py
django_ace_widget/migrations/__init__.py
django_ace_widget/static/django_ace_widget/ace_widget.css
django_ace_widget/static/django_ace_widget/ace_widget.js
django_ace_widget-0.1.0.dist-info/LICENSE
django_ace_widget-0.1.0.dist-info/METADATA
django_ace_widget-0.1.0.dist-info/WHEEL
django_ace_widget-0.1.0.dist-info/top_level.txt
django_ace_widget-0.1.0.dist-info/RECORD
