Metadata-Version: 2.1
Name: django-ace-widget
Version: 0.1.0
Summary: Django admin widget using ACE editor for TextField.
Author: rRR0VrFP
Maintainer: rRR0VrFP
License: Apache License, Version 2.0
Keywords: django admin,django widget,ace editor,django ace widget
Classifier: Development Status :: 5 - Production/Stable
Classifier: Intended Audience :: Developers
Classifier: Topic :: Software Development :: Libraries :: Python Modules
Classifier: License :: OSI Approved :: Apache Software License
Classifier: Programming Language :: Python :: 3
Classifier: Programming Language :: Python :: 3 :: Only
License-File: LICENSE
Requires-Dist: django
Requires-Dist: django-app-requires
Requires-Dist: django-static-ace-builds
